rayures/__init__.py
rayures/_version.py
rayures/admin.py
rayures/apps.py
rayures/events.py
rayures/exceptions.py
rayures/factories.py
rayures/fields.py
rayures/instrumentation.py
rayures/integration.py
rayures/models.py
rayures/objs.py
rayures/prio.py
rayures/reconciliation.py
rayures/stripe_webhooks.py
rayures/tasks.py
rayures/urls.py
rayures/utils.py
rayures/views.py
rayures/management/__init__.py
rayures/management/commands/__init__.py
rayures/management/commands/replay_events.py
rayures/management/commands/sync_stripe_events.py
rayures/migrations/0001_squashed_0005_auto_20180630_2251.py
rayures/migrations/0002_orderreturn.py
rayures/migrations/0003_auto_20180710_1105.py
rayures/migrations/__init__.py
rayures-0.4a25.dist-info/METADATA
rayures-0.4a25.dist-info/RECORD
rayures-0.4a25.dist-info/WHEEL
rayures-0.4a25.dist-info/top_level.txt
