Metadata-Version: 2.1
Name: rayures
Version: 0.4a25
Summary: Integrate stripe into django application
Home-page: https://lab.errorist.xyz/django/rayures
Author: Xavier Barbosa
Author-email: clint.northwood@gmail.com
License: MIT
Platform: UNKNOWN
Classifier: Development Status :: 4 - Beta
Classifier: Framework :: Django
Classifier: Intended Audience :: Developers
Classifier: License :: OSI Approved :: MIT License
Classifier: Programming Language :: Python :: 3.6
Classifier: Programming Language :: Python :: 3.7
Classifier: Topic :: Internet :: WWW/HTTP :: Dynamic Content :: Content Management System
Classifier: Topic :: Office/Business :: Financial
Classifier: Topic :: Software Development :: Libraries :: Python Modules
Provides-Extra: factories
Requires-Dist: stripe (>=1.82.1)
Provides-Extra: factories
Requires-Dist: factory-boy (>=2.11.1); extra == 'factories'
